o2tuner/__init__.py
o2tuner/argumentparser.py
o2tuner/backends.py
o2tuner/config.py
o2tuner/graph.py
o2tuner/inspector.py
o2tuner/io.py
o2tuner/log.py
o2tuner/optimise.py
o2tuner/run.py
o2tuner/sampler.py
o2tuner/system.py
o2tuner/tuner.py
o2tuner/utils.py
o2tuner-0.0.2.dist-info/LICENSE
o2tuner-0.0.2.dist-info/METADATA
o2tuner-0.0.2.dist-info/WHEEL
o2tuner-0.0.2.dist-info/entry_points.txt
o2tuner-0.0.2.dist-info/top_level.txt
o2tuner-0.0.2.dist-info/RECORD
